odoo10_addon_pos_order_return-10.0.1.0.1-py3.8-nspkg.pth
odoo/addons/pos_order_return/README.rst
odoo/addons/pos_order_return/__init__.py
odoo/addons/pos_order_return/__manifest__.py
odoo/addons/pos_order_return/demo/product_product.xml
odoo/addons/pos_order_return/i18n/ca.po
odoo/addons/pos_order_return/i18n/es.po
odoo/addons/pos_order_return/i18n/fr.po
odoo/addons/pos_order_return/i18n/pos_order_return.pot
odoo/addons/pos_order_return/models/__init__.py
odoo/addons/pos_order_return/models/pos_order.py
odoo/addons/pos_order_return/models/product_template.py
odoo/addons/pos_order_return/static/description/icon.png
odoo/addons/pos_order_return/static/description/initial_pos_order_required.png
odoo/addons/pos_order_return/static/description/partial_return_wizard.png
odoo/addons/pos_order_return/static/description/product_returnable_bottle.png
odoo/addons/pos_order_return/static/description/returned_qty_over_initial.png
odoo/addons/pos_order_return/static/description/sum_returned_qty_over_initial.png
odoo/addons/pos_order_return/static/img/product_returnable_bottle-image.jpg
odoo/addons/pos_order_return/tests/__init__.py
odoo/addons/pos_order_return/tests/test_pos_order_return.py
odoo/addons/pos_order_return/views/pos_order_view.xml
odoo/addons/pos_order_return/views/product_product_view.xml
odoo/addons/pos_order_return/wizard/__init__.py
odoo/addons/pos_order_return/wizard/pos_partial_return_wizard.py
odoo/addons/pos_order_return/wizard/pos_partial_return_wizard_view.xml
odoo10_addon_pos_order_return-10.0.1.0.1.dist-info/METADATA
odoo10_addon_pos_order_return-10.0.1.0.1.dist-info/WHEEL
odoo10_addon_pos_order_return-10.0.1.0.1.dist-info/namespace_packages.txt
odoo10_addon_pos_order_return-10.0.1.0.1.dist-info/top_level.txt
odoo10_addon_pos_order_return-10.0.1.0.1.dist-info/RECORD
